sheets/__init__.py
sheets/__main__.py
sheets/bot.py
sheets/core.py
sheets/ident.py
sheets/prepare.py
sheets/stockpile.py
sheets/utools.py
foxhole_sheets-3.0.1.dist-info/LICENSE
foxhole_sheets-3.0.1.dist-info/METADATA
foxhole_sheets-3.0.1.dist-info/WHEEL
foxhole_sheets-3.0.1.dist-info/top_level.txt
foxhole_sheets-3.0.1.dist-info/RECORD
