Metadata-Version: 2.1
Name: foxhole-sheets
Version: 3.0.1
Summary: Foxhole Stockpile Parsing
Home-page: https://github.com/miles-igd/foxhole-sheets
Author: miles-igd
License: MIT
Platform: UNKNOWN
License-File: LICENSE
Requires-Dist: opencv-python
